supercell_slack-0.0.3.dist-info/DESCRIPTION.rst
supercell_slack-0.0.3.dist-info/METADATA
supercell_slack-0.0.3.dist-info/RECORD
supercell_slack-0.0.3.dist-info/WHEEL
supercell_slack-0.0.3.dist-info/metadata.json
supercell_slack-0.0.3.dist-info/top_level.txt
support_bot/__init__.py
