Metadata-Version: 2.0
Name: supercell-slack
Version: 0.0.3
Summary: UNKNOWN
Home-page: UNKNOWN
Author: Scott Snyder
Author-email: scott.snyder@capitalone.com
License: Creative Commons Attribution-Noncommercial-Share Alike license
Platform: UNKNOWN
